LICENSE
MANIFEST.in
README.rst
setup.py
psukys_remoto.egg-info/PKG-INFO
psukys_remoto.egg-info/SOURCES.txt
psukys_remoto.egg-info/dependency_links.txt
psukys_remoto.egg-info/not-zip-safe
psukys_remoto.egg-info/requires.txt
psukys_remoto.egg-info/top_level.txt
remoto/__init__.py
remoto/connection.py
remoto/exc.py
remoto/file_sync.py
remoto/log.py
remoto/process.py
remoto/util.py
remoto/tests/__init__.py
remoto/tests/fake_module.py
remoto/tests/test_connection.py
remoto/tests/test_log.py
remoto/tests/test_process.py
remoto/tests/test_rsync.py
remoto/tests/test_util.py