Metadata-Version: 1.1
Name: psukys-remoto
Version: 0.0.31
Summary: Execute remote commands or processes. Fork with changes to allow continuous output for remote functions
Home-page: http://github.com/psukys/remoto
Author: Alfredo Deza, Paulius Sukys
Author-email: contact@deza.pe, paul.sukys@gmail.com
License: MIT
Keywords: remote,commands,unix,ssh,socket,execute,terminal
Platform: UNKNOWN
Classifier: Development Status :: 4 - Beta
Classifier: Intended Audience :: Developers
Classifier: License :: OSI Approved :: MIT License
Classifier: Topic :: Utilities
Classifier: Operating System :: MacOS :: MacOS X
Classifier: Operating System :: POSIX
Classifier: Programming Language :: Python :: 2.6
Classifier: Programming Language :: Python :: 2.7
Classifier: Programming Language :: Python :: 3.3
